pygel3d/PyGEL.dll
pygel3d/__init__.py
pygel3d/gl_display.py
pygel3d/graph.py
pygel3d/hmesh.py
pygel3d/jupyter_display.py
pygel3d/libPyGEL.dylib
pygel3d/libPyGEL.so
pygel3d/spatial.py
PyGEL3D-0.6.0.dist-info/LICENSE.md
PyGEL3D-0.6.0.dist-info/METADATA
PyGEL3D-0.6.0.dist-info/WHEEL
PyGEL3D-0.6.0.dist-info/top_level.txt
PyGEL3D-0.6.0.dist-info/RECORD
