Metadata-Version: 2.1
Name: PyGEL3D
Version: 0.6.0
Summary: PyGEL 3D (Python Bindings for GEL) contains tools for polygonal mesh based geometry processing
Home-page: http://www2.compute.dtu.dk/projects/GEL/PyGEL/
Author: Andreas Baerentzen
Author-email: janba@dtu.dk
Classifier: Programming Language :: Python :: 3
Classifier: Operating System :: Microsoft :: Windows
Classifier: Operating System :: MacOS
Classifier: Operating System :: POSIX :: Linux
License-File: LICENSE.md
Requires-Dist: numpy
Requires-Dist: plotly ==5.24.1
Requires-Dist: scipy
